Metadata-Version: 2.1
Name: synapsectl
Version: 0.1.0
Summary: A more convenient way to run matrix-synapse admin commands
Home-page: https://git.sr.ht/~martijnbraam/synapsectl
Author: Martijn Braam
Author-email: martijn@brixit.nl
License: GPL3
License-File: LICENSE
